gp2040ce_bintools/__init__.py
gp2040ce_bintools/_version.py
gp2040ce_bintools/builder.py
gp2040ce_bintools/config_tree.css
gp2040ce_bintools/gui.py
gp2040ce_bintools/rp2040.py
gp2040ce_bintools/storage.py
gp2040ce_bintools/proto_snapshot/config.proto
gp2040ce_bintools/proto_snapshot/enums.proto
gp2040ce_bintools/proto_snapshot/nanopb.proto
gp2040ce_binary_tools-0.11.0.dist-info/LICENSE.md
gp2040ce_binary_tools-0.11.0.dist-info/METADATA
gp2040ce_binary_tools-0.11.0.dist-info/WHEEL
gp2040ce_binary_tools-0.11.0.dist-info/entry_points.txt
gp2040ce_binary_tools-0.11.0.dist-info/top_level.txt
gp2040ce_binary_tools-0.11.0.dist-info/RECORD
