Metadata-Version: 2.1
Name: gp2040ce-binary-tools
Version: 0.11.0
Summary: Tools for working with GP2040-CE firmware and storage binaries.
Author-email: "Brian S. Stephan" <bss@incorporeal.org>
License: GPL-3.0-or-later
Project-URL: Homepage, https://github.com/OpenStickCommunity/gp2040ce-binary-tools
Project-URL: Changelog, https://github.com/OpenStickCommunity/gp2040ce-binary-tools/blob/main/CHANGELOG.md
Project-URL: Bug Tracker, https://github.com/OpenStickCommunity/gp2040ce-binary-tools/issues
Classifier: Environment :: Console
Classifier: Programming Language :: Python :: 3
Classifier: License :: OSI Approved :: GNU General Public License v3 or later (GPLv3+)
Classifier: Operating System :: OS Independent
Classifier: Topic :: Utilities
Requires-Python: >=3.9
License-File: LICENSE.md
Requires-Dist: grpcio-tools
Requires-Dist: pyusb
Requires-Dist: textual
Provides-Extra: dev
Requires-Dist: bandit; extra == "dev"
Requires-Dist: decorator; extra == "dev"
Requires-Dist: flake8; extra == "dev"
Requires-Dist: flake8-blind-except; extra == "dev"
Requires-Dist: flake8-builtins; extra == "dev"
Requires-Dist: flake8-docstrings; extra == "dev"
Requires-Dist: flake8-executable; extra == "dev"
Requires-Dist: flake8-fixme; extra == "dev"
Requires-Dist: flake8-isort; extra == "dev"
Requires-Dist: flake8-logging-format; extra == "dev"
Requires-Dist: flake8-mutable; extra == "dev"
Requires-Dist: flake8-pyproject; extra == "dev"
Requires-Dist: mypy; extra == "dev"
Requires-Dist: pip-tools; extra == "dev"
Requires-Dist: pytest; extra == "dev"
Requires-Dist: pytest-asyncio; extra == "dev"
Requires-Dist: pytest-cov; extra == "dev"
Requires-Dist: reuse; extra == "dev"
Requires-Dist: setuptools-scm; extra == "dev"
Requires-Dist: textual-dev; extra == "dev"
Requires-Dist: tox; extra == "dev"
Requires-Dist: twine; extra == "dev"
